girder_wholetale/__init__.py
girder_wholetale/constants.py
girder_wholetale/utils.py
girder_wholetale/lib/__init__.py
girder_wholetale/lib/cache_manager.py
girder_wholetale/lib/data_map.py
girder_wholetale/lib/entity.py
girder_wholetale/lib/events.py
girder_wholetale/lib/file_gc.py
girder_wholetale/lib/file_map.py
girder_wholetale/lib/handler_factory.py
girder_wholetale/lib/http_provider.py
girder_wholetale/lib/import_item.py
girder_wholetale/lib/import_providers.py
girder_wholetale/lib/integration_utils.py
girder_wholetale/lib/license.py
girder_wholetale/lib/manifest.py
girder_wholetale/lib/manifest_parser.py
girder_wholetale/lib/metrics.py
girder_wholetale/lib/null_provider.py
girder_wholetale/lib/orcid.py
girder_wholetale/lib/path_mapper.py
girder_wholetale/lib/path_mappers.py
girder_wholetale/lib/resolvers.py
girder_wholetale/lib/tm_utils.py
girder_wholetale/lib/transfer_manager.py
girder_wholetale/lib/verificator.py
girder_wholetale/lib/bdbag/__init__.py
girder_wholetale/lib/bdbag/bdbag_provider.py
girder_wholetale/lib/dataverse/__init__.py
girder_wholetale/lib/dataverse/auth.py
girder_wholetale/lib/dataverse/installations.json
girder_wholetale/lib/dataverse/integration.py
girder_wholetale/lib/dataverse/provider.py
girder_wholetale/lib/exporters/__init__.py
girder_wholetale/lib/exporters/bag.py
girder_wholetale/lib/exporters/native.py
girder_wholetale/lib/handlers/__init__.py
girder_wholetale/lib/handlers/common.py
girder_wholetale/lib/handlers/http.py
girder_wholetale/lib/handlers/local.py
girder_wholetale/lib/openicpsr/__init__.py
girder_wholetale/lib/openicpsr/auth.py
girder_wholetale/lib/openicpsr/provider.py
girder_wholetale/lib/zenodo/__init__.py
girder_wholetale/lib/zenodo/auth.py
girder_wholetale/lib/zenodo/integration.py
girder_wholetale/lib/zenodo/provider.py
girder_wholetale/models/__init__.py
girder_wholetale/models/hierarchy.py
girder_wholetale/models/image.py
girder_wholetale/models/instance.py
girder_wholetale/models/lock.py
girder_wholetale-2.0.10.dist-info/licenses/LICENSE
girder_wholetale-2.0.10.dist-info/METADATA
girder_wholetale-2.0.10.dist-info/WHEEL
girder_wholetale-2.0.10.dist-info/entry_points.txt
girder_wholetale-2.0.10.dist-info/top_level.txt
girder_wholetale-2.0.10.dist-info/RECORD
