Metadata-Version: 2.4
Name: girder-wholetale
Version: 2.0.10
Summary: Girder plugin implementing Whole Tale core functionality.
License: Apache 2.0
Classifier: Development Status :: 4 - Beta
Classifier: Environment :: Web Environment
Classifier: License :: OSI Approved :: Apache Software License
Classifier: Operating System :: POSIX :: Linux
Classifier: Programming Language :: Python
Classifier: Programming Language :: Python :: 3
Requires-Python: >=3.10
License-File: LICENSE
Requires-Dist: girder>=5.0.0a10.dev8
Requires-Dist: girder-jobs>=5.0.0a10.dev8
Requires-Dist: girder-plugin-worker>=5.0.0a10.dev8
Requires-Dist: girder-virtual-resources
Requires-Dist: girder-oauth>=5.0.0a10.dev8
Requires-Dist: rdflib
Requires-Dist: celery[redis]
Requires-Dist: pathvalidate
Requires-Dist: influxdb-client
Requires-Dist: python-magic
Requires-Dist: requests
Requires-Dist: validators
Requires-Dist: html2markdown
Requires-Dist: lxml_html_clean
Requires-Dist: GitPython
Requires-Dist: httpio>=0.3.0
Requires-Dist: fs
Requires-Dist: gwvolman>=2.1.2
Dynamic: classifier
Dynamic: description
Dynamic: description-content-type
Dynamic: license
Dynamic: license-file
Dynamic: requires-dist
Dynamic: requires-python
Dynamic: summary
